auto_vicuna_its_alive_plugin/__init__.py
auto_vicuna_its_alive_plugin-0.0.1.dist-info/METADATA
auto_vicuna_its_alive_plugin-0.0.1.dist-info/WHEEL
auto_vicuna_its_alive_plugin-0.0.1.dist-info/licenses/LICENSE
auto_vicuna_its_alive_plugin-0.0.1.dist-info/RECORD
